pyryotype/__about__.py
pyryotype/__init__.py
pyryotype/coverage.py
pyryotype/ideogram.py
pyryotype/paf_plotting.py
pyryotype/paf_tools.py
pyryotype/plotting_utils.py
pyryotype/static/cytobands_chm13.bed
pyryotype/static/cytobands_hg38.bed
pyryotype-0.0.7.dist-info/METADATA
pyryotype-0.0.7.dist-info/WHEEL
pyryotype-0.0.7.dist-info/licenses/LICENSE.txt
pyryotype-0.0.7.dist-info/RECORD
