Metadata-Version: 2.1
Name: pyryotype
Version: 0.0.7
Summary: Draw an ideogram of either HG38 or CHM13 contigs in a matplotlib axes object.
Project-URL: Documentation, https://github.com/adoni5/ideogram#readme
Project-URL: Issues, https://github.com/adoni5/ideogram/issues
Project-URL: Source, https://github.com/adoni5/ideogram
Author-email: Adoni5 <roryjmunro1@gmail.com>
License-File: LICENSE.txt
Classifier: Development Status :: 4 - Beta
Classifier: Intended Audience :: Science/Research
Classifier: License :: OSI Approved :: MIT License
Classifier: Natural Language :: English
Classifier: Operating System :: OS Independent
Classifier: Programming Language :: Python
Classifier: Programming Language :: Python :: 3.10
Classifier: Programming Language :: Python :: 3.11
Classifier: Programming Language :: Python :: Implementation :: CPython
Classifier: Programming Language :: Python :: Implementation :: PyPy
Classifier: Topic :: Scientific/Engineering :: Bio-Informatics
Requires-Python: >=3.10
Requires-Dist: matplotlib
Requires-Dist: numpy
Requires-Dist: pandas
Provides-Extra: dev
Requires-Dist: black>=23.1.0; extra == 'dev'
Requires-Dist: coverage[toml]>=6.5; extra == 'dev'
Requires-Dist: isort; extra == 'dev'
Requires-Dist: mypy>=1.0.0; extra == 'dev'
Requires-Dist: pre-commit; extra == 'dev'
Requires-Dist: pyryotype[paf]; extra == 'dev'
Requires-Dist: pytest; extra == 'dev'
Requires-Dist: ruff>=0.0.243; extra == 'dev'
Provides-Extra: paf
Requires-Dist: readpaf; extra == 'paf'
